django_rest_multiple_models-2.1.3.dist-info/METADATA
django_rest_multiple_models-2.1.3.dist-info/RECORD
django_rest_multiple_models-2.1.3.dist-info/WHEEL
django_rest_multiple_models-2.1.3.dist-info/top_level.txt
drf_multiple_model/__init__.py
drf_multiple_model/mixins.py
drf_multiple_model/models.py
drf_multiple_model/pagination.py
drf_multiple_model/views.py
drf_multiple_model/viewsets.py
